kanjigrid/__init__.py
kanjigrid/gradings.py
kanjigrid/kanjigrid.py
kanjigrid-0.0.5.dist-info/entry_points.txt
kanjigrid-0.0.5.dist-info/LICENSE
kanjigrid-0.0.5.dist-info/WHEEL
kanjigrid-0.0.5.dist-info/METADATA
kanjigrid-0.0.5.dist-info/RECORD
